insuant/__init__.py
insuant/__main__.py
insuant/alembic/alembic.log
insuant/alembic/env.py
insuant/alembic/README
insuant/alembic/script.py.mako
insuant/alembic/versions/006b3990db50_add_unique_constraints.py
insuant/alembic/versions/0b8757876a7c_.py
insuant/alembic/versions/1a110b568907_replace_credential_table_with_variable.py
insuant/alembic/versions/1ef9c4f3765d_.py
insuant/alembic/versions/260dbcc8b680_adds_tables.py
insuant/alembic/versions/2ac71eb9c3ae_adds_credential_table.py
insuant/alembic/versions/63b9c451fd30_add_icon_and_icon_bg_color_to_flow.py
insuant/alembic/versions/67cc006d50bf_add_profile_image_column.py
insuant/alembic/versions/7843803a87b5_store_updates.py
insuant/alembic/versions/79e675cb6752_change_datetime_type.py
insuant/alembic/versions/7d2162acc8b2_adds_updated_at_and_folder_cols.py
insuant/alembic/versions/b2fa308044b5_add_unique_constraints.py
insuant/alembic/versions/bc2f01c40e4a_new_fixes.py
insuant/alembic/versions/e3bc869fa272_fix_nullable.py
insuant/alembic/versions/eb5866d51fd2_change_columns_to_be_nullable.py
insuant/alembic/versions/f5ee9749d1a6_user_id_can_be_null_in_flow.py
insuant/alembic/versions/fd531f8868b1_fix_credential_table.py
insuant/alembic.ini
insuant/api/__init__.py
insuant/api/router.py
insuant/api/utils.py
insuant/api/v1/__init__.py
insuant/api/v1/account.py
insuant/api/v1/api_key.py
insuant/api/v1/api_limit.py
insuant/api/v1/auth.py
insuant/api/v1/base.py
insuant/api/v1/callback.py
insuant/api/v1/chat.py
insuant/api/v1/chats.py
insuant/api/v1/documents.py
insuant/api/v1/endpoints.py
insuant/api/v1/files.py
insuant/api/v1/flowPublish.py
insuant/api/v1/flows.py
insuant/api/v1/interact.py
insuant/api/v1/login.py
insuant/api/v1/monitor.py
insuant/api/v1/schemas.py
insuant/api/v1/store.py
insuant/api/v1/subscription.py
insuant/api/v1/users.py
insuant/api/v1/validate.py
insuant/api/v1/variable.py
insuant/base/__init__.py
insuant/base/agents/__init__.py
insuant/base/agents/agent.py
insuant/base/constants.py
insuant-1.0.0a20.dist-info/entry_points.txt
insuant-1.0.0a20.dist-info/METADATA
insuant-1.0.0a20.dist-info/WHEEL
insuant-1.0.0a20.dist-info/RECORD
