Metadata-Version: 2.1
Name: insuant
Version: 1.0.0a20
Summary: A Python package with a built-in web application
Home-page: https://github.com/langflow-ai/langflow
License: MIT
Keywords: nlp,langchain,openai,gpt,gui
Author: Logspace
Author-email: contact@logspace.ai
Maintainer: Carlos Coelho
Maintainer-email: carlos@logspace.ai
Requires-Python: >=3.10,<3.12
Classifier: License :: OSI Approved :: MIT License
Classifier: Programming Language :: Python :: 3
Classifier: Programming Language :: Python :: 3.10
Classifier: Programming Language :: Python :: 3.11
Provides-Extra: deploy
Provides-Extra: local
Requires-Dist: PyHive (>=0.7.0,<0.8.0)
Requires-Dist: PyMuPDF (>=1.23.26,<2.0.0)
Requires-Dist: PyMuPDFb (>=1.23.22,<2.0.0)
Requires-Dist: PyPDF2 (>=3.0.1,<4.0.0)
Requires-Dist: PyPika (>=0.48.9,<0.49.0)
Requires-Dist: Pygments (>=2.17.2,<3.0.0)
Requires-Dist: SQLAlchemy (>=2.0.25,<3.0.0)
Requires-Dist: aio-pika (==9.4.0)
Requires-Dist: aiofiles (==23.2.1)
Requires-Dist: aiohttp (==3.9.5)
Requires-Dist: aiokafka (==0.8.1)
Requires-Dist: aiormq (==6.8.0)
Requires-Dist: aiosignal (==1.3.1)
Requires-Dist: alembic (>=1.13.0,<2.0.0)
Requires-Dist: altair (==5.2.0)
Requires-Dist: annotated-types (==0.6.0)
Requires-Dist: antlr4-python3-runtime (==4.9.3)
Requires-Dist: anyio (==4.3.0)
Requires-Dist: appnope (==0.1.4)
Requires-Dist: asgiref (==3.8.1)
Requires-Dist: assemblyai (>=0.23.1,<0.24.0)
Requires-Dist: astor (==0.8.1)
Requires-Dist: asttokens (==2.4.1)
Requires-Dist: async-timeout (==4.0.3)
Requires-Dist: asyncer (>=0.0.5,<0.0.6)
Requires-Dist: asyncpg (==0.28.0)
Requires-Dist: attrs (==23.2.0)
Requires-Dist: autoflake (==1.7.8)
Requires-Dist: backoff (==2.2.1)
Requires-Dist: bandit (==1.7.7)
Requires-Dist: bcrypt (==4.1.2)
Requires-Dist: beautifulsoup4 (>=4.12.2,<5.0.0)
Requires-Dist: black (==22.12.0)
Requires-Dist: blinker (==1.7.0)
Requires-Dist: boto3 (>=1.34.0,<2.0.0)
Requires-Dist: bs4 (==0.0.2)
Requires-Dist: build (==1.0.3)
Requires-Dist: celery[redis] (>=5.3.6,<6.0.0) ; extra == "deploy"
Requires-Dist: certifi (>=2023.11.17,<2024.0.0)
Requires-Dist: chromadb (>=0.4.24,<0.5.0)
Requires-Dist: cohere (>=5.1.7,<6.0.0)
Requires-Dist: cryptography (>=42.0.5,<43.0.0)
Requires-Dist: ctransformers (>=0.2.10,<0.3.0) ; extra == "local"
Requires-Dist: docstring-parser (>=0.15,<0.16)
Requires-Dist: dspy-ai (>=2.4.4,<3.0.0)
Requires-Dist: duckdb (>=0.9.2,<0.10.0)
Requires-Dist: elasticsearch (>=8.12.0,<9.0.0)
Requires-Dist: emoji (>=2.11.0,<3.0.0)
Requires-Dist: extract-msg (>=0.47.0,<0.48.0)
Requires-Dist: faiss-cpu (>=1.7.4,<2.0.0)
Requires-Dist: fake-useragent (>=1.4.0,<2.0.0)
Requires-Dist: fastapi (>=0.110.1,<0.111.0)
Requires-Dist: fastavro (>=1.8.0,<2.0.0)
Requires-Dist: flower (>=2.0.0,<3.0.0) ; extra == "deploy"
Requires-Dist: google-api-python-client (>=2.118.0,<3.0.0)
Requires-Dist: google-generativeai (>=0.4.1,<0.5.0)
Requires-Dist: google-search-results (>=2.4.1,<3.0.0)
Requires-Dist: gunicorn (>=21.2.0,<22.0.0)
Requires-Dist: html2text (>=2024.2.26,<2025.0.0)
Requires-Dist: huggingface-hub[inference] (>=0.20.0,<0.21.0)
Requires-Dist: jq (>=1.7.0,<2.0.0) ; sys_platform != "win32"
Requires-Dist: langchain (>=0.1.10,<0.2.0)
Requires-Dist: langchain-anthropic (>=0.1.6,<0.2.0)
Requires-Dist: langchain-astradb (>=0.1.0,<0.2.0)
Requires-Dist: langchain-cohere (>=0.1.0rc1,<0.2.0)
Requires-Dist: langchain-community (>=0.0.30,<0.0.31)
Requires-Dist: langchain-core (>=0.1.28,<0.2.0)
Requires-Dist: langchain-experimental
Requires-Dist: langchain-google-genai (>=1.0.1,<2.0.0)
Requires-Dist: langchain-openai (>=0.1.1,<0.2.0)
Requires-Dist: langfuse (>=2.9.0,<3.0.0)
Requires-Dist: litellm (>=1.34.22,<2.0.0)
Requires-Dist: llama-cpp-python (>=0.2.0,<0.3.0) ; extra == "local"
Requires-Dist: llama-index (>=0.10.18,<0.11.0)
Requires-Dist: llama-index-embeddings-openai (>=0.1.6,<0.2.0)
Requires-Dist: llama-parse (>=0.3.8,<0.4.0)
Requires-Dist: llm (==0.14)
Requires-Dist: loguru (>=0.7.1,<0.8.0)
Requires-Dist: markupsafe (>=2.1.3,<3.0.0)
Requires-Dist: metal-sdk (>=2.5.0,<3.0.0)
Requires-Dist: metaphor-python (>=0.1.11,<0.2.0)
Requires-Dist: multiprocess (>=0.70.14,<0.71.0)
Requires-Dist: nest-asyncio (>=1.6.0,<2.0.0)
Requires-Dist: networkx (>=3.1,<4.0)
Requires-Dist: numexpr (>=2.8.6,<3.0.0)
Requires-Dist: onnx (>=1.15.0,<2.0.0)
Requires-Dist: onnxruntime (>=1.15.1,<2.0.0)
Requires-Dist: openai (>=1.13.3,<2.0.0)
Requires-Dist: opencv-python (>=4.9.0.80,<5.0.0.0)
Requires-Dist: openpyxl (>=3.1.2,<4.0.0)
Requires-Dist: opentelemetry-api (>=1.23.0,<2.0.0)
Requires-Dist: opentelemetry-exporter-otlp-proto-common (>=1.23.0,<2.0.0)
Requires-Dist: opentelemetry-exporter-otlp-proto-grpc (>=1.23.0,<2.0.0)
Requires-Dist: opentelemetry-exporter-otlp-proto-http (>=1.23.0,<2.0.0)
Requires-Dist: opentelemetry-instrumentation (>=0.44b0,<0.45)
Requires-Dist: opentelemetry-instrumentation-asgi (>=0.44b0,<0.45)
Requires-Dist: opentelemetry-instrumentation-fastapi (>=0.44b0,<0.45)
Requires-Dist: opentelemetry-proto (>=1.23.0,<2.0.0)
Requires-Dist: opentelemetry-sdk (>=1.23.0,<2.0.0)
Requires-Dist: opentelemetry-semantic-conventions (>=0.44b0,<0.45)
Requires-Dist: opentelemetry-util-http (>=0.44b0,<0.45)
Requires-Dist: orjson (==3.10.0)
Requires-Dist: pandas (==2.2.0)
Requires-Dist: passlib (>=1.7.4,<2.0.0)
Requires-Dist: pdf2image (>=1.17.0,<2.0.0)
Requires-Dist: pdfminer-six (>=20231228,<20231229)
Requires-Dist: pdfplumber (==0.11.1)
Requires-Dist: pgvector (>=0.2.3,<0.3.0)
Requires-Dist: pikepdf (>=8.13.0,<9.0.0)
Requires-Dist: pillow (>=10.2.0,<11.0.0)
Requires-Dist: pillow_heif (>=0.15.0,<0.16.0)
Requires-Dist: pinecone-client (>=3.0.3,<4.0.0)
Requires-Dist: platformdirs (>=4.2.0,<5.0.0)
Requires-Dist: presto-python-client (==0.8.4)
Requires-Dist: psycopg (>=3.1.9,<4.0.0)
Requires-Dist: psycopg-binary (>=3.1.9,<4.0.0)
Requires-Dist: psycopg2-binary (>=2.9.6,<3.0.0)
Requires-Dist: pyarrow (>=14.0.0,<15.0.0)
Requires-Dist: pyautogen (>=0.2.0,<0.3.0)
Requires-Dist: pydantic (>=2.5.0,<3.0.0)
Requires-Dist: pydantic-settings (>=2.1.0,<3.0.0)
Requires-Dist: pydantic_core (>=2.14.1,<3.0.0)
Requires-Dist: pydocstyle (>=6.3.0,<7.0.0)
Requires-Dist: pydub (>=0.25.1,<0.26.0)
Requires-Dist: pyflakes (>=2.4.0,<3.0.0)
Requires-Dist: pymongo (>=4.6.0,<5.0.0)
Requires-Dist: pypandoc (>=1.12,<2.0)
Requires-Dist: pypdf (>=4.0.1,<5.0.0)
Requires-Dist: pypdfium2 (>=4.27.0,<5.0.0)
Requires-Dist: pyproject_hooks (==1.0.0)
Requires-Dist: pysrt (>=1.1.2,<2.0.0)
Requires-Dist: pytesseract (==0.3.10)
Requires-Dist: pytest-cov (>=4.1.0,<5.0.0)
Requires-Dist: pytest-env (==0.8.2)
Requires-Dist: python-dateutil (==2.8.2)
Requires-Dist: python-docx (==1.1.0)
Requires-Dist: python-dotenv (==1.0.0)
Requires-Dist: python-iso639 (==2024.2.7)
Requires-Dist: python-jose (==3.3.0)
Requires-Dist: python-magic (==0.4.27)
Requires-Dist: python-multipart (>=0.0.9,<0.0.10)
Requires-Dist: python-socketio (>=5.11.0,<6.0.0)
Requires-Dist: pytube (>=15.0.0,<16.0.0)
Requires-Dist: pywin32 (>=306,<307) ; sys_platform == "win32"
Requires-Dist: qdrant-client (>=1.7.0,<2.0.0)
Requires-Dist: qianfan (==0.3.5)
Requires-Dist: redis (>=5.0.1,<6.0.0) ; extra == "deploy"
Requires-Dist: rich (>=13.7.0,<14.0.0)
Requires-Dist: sentence-transformers (>=2.3.1,<3.0.0) ; extra == "local"
Requires-Dist: sqlmodel (>=0.0.16,<0.0.17)
Requires-Dist: starlette (>=0.37.2,<0.38.0)
Requires-Dist: streamlit (>=1.31.0,<2.0.0)
Requires-Dist: supabase (>=2.3.0,<3.0.0)
Requires-Dist: tavily-python (==0.3.3)
Requires-Dist: typer (>=0.12.0,<0.13.0)
Requires-Dist: types-cachetools (>=5.3.0.5,<6.0.0.0)
Requires-Dist: types-requests (>=2.31.0.20240218,<3.0.0.0)
Requires-Dist: typing-inspect (>=0.9.0,<0.10.0)
Requires-Dist: typing_extensions (>=4.9.0,<5.0.0)
Requires-Dist: unstructured[md] (>=0.12.4,<0.13.0)
Requires-Dist: uvicorn (>=0.29.0,<0.30.0)
Requires-Dist: weaviate-client
Requires-Dist: websockets
Requires-Dist: wikipedia (>=1.4.0,<2.0.0)
Project-URL: Documentation, https://docs.langflow.org
Project-URL: Repository, https://github.com/langflow-ai/langflow
